__init__.py
pychatgpt/__init__.py
pychatgpt/main.py
pychatgpt/classes/chat.py
pychatgpt/classes/exceptions.py
pychatgpt/classes/headers.py
pychatgpt/classes/openai.py
pychatgpt/classes/spinner.py
chatgptpy-1.0.8.dist-info/LICENSE
chatgptpy-1.0.8.dist-info/METADATA
chatgptpy-1.0.8.dist-info/WHEEL
chatgptpy-1.0.8.dist-info/top_level.txt
chatgptpy-1.0.8.dist-info/RECORD
