Metadata-Version: 2.1
Name: chatgptpy
Version: 1.0.8
Summary: ⚡️TLS-based ChatGPT API with auto token regeneration, conversation tracking, proxy support and more.
Author-email: Rawand Ahmed Shaswar <pychatgpt@rawa.dev>
Project-URL: Homepage, https://github.com/rawandahmad698/PyChatGPT
Project-URL: Bug Tracker, https://github.com/rawandahmad698/PyChatGPT/issues
Classifier: Programming Language :: Python :: 3
Classifier: License :: OSI Approved :: MIT License
Classifier: Operating System :: OS Independent
Requires-Python: >=3.9
License-File: LICENSE
